langfn/__init__.py
langfn/client.py
langfn/agents/__init__.py
langfn/agents/react.py
langfn/agents/tool_agent.py
langfn/core/__init__.py
langfn/core/errors.py
langfn/core/types.py
langfn/evaluation/__init__.py
langfn/evaluation/dataset.py
langfn/evaluation/evaluator.py
langfn/evaluation/metrics.py
langfn/graph/__init__.py
langfn/graph/state_graph.py
langfn/http/__init__.py
langfn/http/handlers.py
langfn/http/routes.py
langfn/mcp/__init__.py
langfn/mcp/client.py
langfn/mcp/server.py
langfn/mcp/stdio.py
langfn/mcp/types.py
langfn/memory/__init__.py
langfn/memory/buffer.py
langfn/memory/summary.py
langfn/models/__init__.py
langfn/models/anthropic.py
langfn/models/base.py
langfn/models/mock.py
langfn/models/ollama.py
langfn/models/openai.py
langfn/observability/__init__.py
langfn/observability/budgets.py
langfn/observability/cost_meter.py
langfn/observability/exporter.py
langfn/observability/redaction.py
langfn/observability/span_types.py
langfn/observability/storage.py
langfn/observability/tracer.py
langfn/orchestration/__init__.py
langfn/orchestration/chain.py
langfn/prompts/__init__.py
langfn/prompts/chat_template.py
langfn/prompts/few_shot.py
langfn/prompts/registry.py
langfn/prompts/template.py
langfn/rag/__init__.py
langfn/rag/base.py
langfn/rag/db_vector_store.py
langfn/rag/memory.py
langfn/rag/openai.py
langfn/storage/__init__.py
langfn/storage/cache.py
langfn/streaming/sse.py
langfn/structured/__init__.py
langfn/structured/output.py
langfn/tools/__init__.py
langfn/tools/api_call.py
langfn/tools/base.py
langfn/tools/calculator.py
langfn/utils/__init__.py
langfn/utils/cancel.py
langfn/utils/concurrency.py
langfn/utils/json.py
langfn/utils/retry.py
langfn/utils/token_counter.py
langfn-0.0.1.dist-info/METADATA
langfn-0.0.1.dist-info/WHEEL
langfn-0.0.1.dist-info/RECORD
